odoo10_addon_sale_fixed_discount-10.0.1.0.1-nspkg.pth
odoo/addons/sale_fixed_discount/README.rst
odoo/addons/sale_fixed_discount/__init__.py
odoo/addons/sale_fixed_discount/__manifest__.py
odoo/addons/sale_fixed_discount/i18n/sale_fixed_discount.pot
odoo/addons/sale_fixed_discount/models/__init__.py
odoo/addons/sale_fixed_discount/models/sale_order.py
odoo/addons/sale_fixed_discount/reports/report_sale_order.xml
odoo/addons/sale_fixed_discount/static/description/icon.png
odoo/addons/sale_fixed_discount/tests/__init__.py
odoo/addons/sale_fixed_discount/tests/test_sale_fixed_discount.py
odoo/addons/sale_fixed_discount/views/sale_order_view.xml
odoo10_addon_sale_fixed_discount-10.0.1.0.1.dist-info/METADATA
odoo10_addon_sale_fixed_discount-10.0.1.0.1.dist-info/WHEEL
odoo10_addon_sale_fixed_discount-10.0.1.0.1.dist-info/namespace_packages.txt
odoo10_addon_sale_fixed_discount-10.0.1.0.1.dist-info/top_level.txt
odoo10_addon_sale_fixed_discount-10.0.1.0.1.dist-info/RECORD
