Metadata-Version: 2.1
Name: odoo10-addon-sale-fixed-discount
Version: 10.0.1.0.1
Summary: Allows to apply fixed amount discounts in sales orders.
Home-page: https://github.com/OCA/sale-workflow
Author: Eficent, Odoo Community Association (OCA)
Author-email: support@odoo-community.org
License: AGPL-3
Platform: UNKNOWN
Classifier: Programming Language :: Python
Classifier: Framework :: Odoo
Classifier: License :: OSI Approved :: GNU Affero General Public License v3
Requires-Python: ~=2.7
Requires-Dist: odoo10-addon-account-invoice-fixed-discount
Requires-Dist: odoo (<10.1dev,>=10.0)
